{"cameraMode":{"drawMode":0,"name":"Shaded","section":"Shading Mode"},"sceneLighting":true,"audioPlay":false,"sceneViewState":{"m_AlwaysRefresh":false,"showFog":true,"showSkybox":true,"showFlares":true,"showImageEffects":true,"showParticleSystems":true,"showVisualEffectGraphs":true,"m_FxEnabled":true},"in2DMode":false,"pivot":{"x":-4.396876811981201,"y":0.868706226348877,"z":11.46869945526123},"rotation":{"x":0.16299808025360108,"y":-0.28758931159973147,"z":0.05009337142109871,"w":0.9427796006202698},"size":4.238495826721191,"orthographic":false}