{"cameraMode":{"drawMode":0,"name":"Shaded","section":"Shading Mode"},"sceneLighting":true,"audioPlay":false,"sceneViewState":{"m_AlwaysRefresh":false,"showFog":true,"showSkybox":true,"showFlares":true,"showImageEffects":true,"showParticleSystems":true,"showVisualEffectGraphs":true,"m_FxEnabled":true},"in2DMode":false,"pivot":{"x":-112.99408721923828,"y":-37.77048110961914,"z":15.999614715576172},"rotation":{"x":-0.12126433849334717,"y":0.6440898776054382,"z":-0.1045907735824585,"w":-0.7481780648231506},"size":65.11737823486328,"orthographic":false}